flake8_patch/__init__.py
flake8_patch/errors.py
flake8_patch/plugin.py
flake8_patch/visitors/__init__.py
flake8_patch/visitors/assignment.py
flake8_patch-0.1.0.dist-info/entry_points.txt
flake8_patch-0.1.0.dist-info/LICENSE
flake8_patch-0.1.0.dist-info/WHEEL
flake8_patch-0.1.0.dist-info/METADATA
flake8_patch-0.1.0.dist-info/RECORD
